SeedsLabeler/SeedsLabeler.py
SeedsLabeler/__init__.py
SeedsLabeler/butta.py
src/__init__.py
src/resources.py
src/api/__init__.py
src/api/detection_client.py
src/api/detection_flask.py
src/api/inference_api.py
src/gui/LabelerWindow.py
src/gui/__init__.py
src/gui/ui_mainwindow.py
src/libs/__init__.py
src/libs/canvas.py
src/libs/category.py
src/libs/colorDialog.py
src/libs/constants.py
src/libs/crashreporter.py
src/libs/file_loader.py
src/libs/hashableQListWidgetItem.py
src/libs/image.py
src/libs/labelDialog.py
src/libs/labelFile.py
src/libs/lib.py
src/libs/pascal_voc_io.py
src/libs/project.py
src/libs/projectDialog.py
src/libs/project_data.py
src/libs/settings.py
src/libs/shape.py
src/libs/stringBundle.py
src/libs/toolBar.py
src/libs/ustr.py
src/libs/version.py
src/libs/yolo_io.py
src/libs/zoom.py
src/libs/zoomWidget.py
SeedsLabeler-0.0.42.dist-info/METADATA
SeedsLabeler-0.0.42.dist-info/WHEEL
SeedsLabeler-0.0.42.dist-info/entry_points.txt
SeedsLabeler-0.0.42.dist-info/top_level.txt
SeedsLabeler-0.0.42.dist-info/RECORD
