Metadata-Version: 2.1
Name: SeedsLabeler
Version: 0.0.42
Summary: Seeds annotation tool
Home-page: https://github.com/meryusha/seeds_labeler/
Author: Merey Ramazanova, Silvio Giancola
Author-email: merey.ramazanova@kaust.edu.sa
License: MIT license
Keywords: TCPClient
Platform: UNKNOWN
Classifier: Development Status :: 5 - Production/Stable
Classifier: Intended Audience :: Developers
Classifier: License :: OSI Approved :: MIT License
Classifier: Natural Language :: English
Classifier: Programming Language :: Python :: 3
Classifier: Programming Language :: Python :: 3.3
Classifier: Programming Language :: Python :: 3.4
Classifier: Programming Language :: Python :: 3.5
Classifier: Programming Language :: Python :: 3.6
Classifier: Programming Language :: Python :: 3.7
Requires-Python: >=3.0.0
Requires-Dist: pyqt5
Requires-Dist: lxml
Requires-Dist: numpy
Requires-Dist: pandas
Requires-Dist: requests
